audiolipsum/__init__.py
audiolipsum/cli.py
audiolipsum/exceptions.py
audiolipsum/helpers.py
audiolipsum/models.py
opawg_audiolipsum-0.1.dist-info/LICENSE
opawg_audiolipsum-0.1.dist-info/METADATA
opawg_audiolipsum-0.1.dist-info/WHEEL
opawg_audiolipsum-0.1.dist-info/entry_points.txt
opawg_audiolipsum-0.1.dist-info/top_level.txt
opawg_audiolipsum-0.1.dist-info/RECORD
