Metadata-Version: 2.1
Name: opawg-audiolipsum
Version: 0.1
Summary: UNKNOWN
Home-page: https://github.com/opawg/audiolipsum
Author: Open Podcast Analytics Working Group
License: MIT
Platform: UNKNOWN
Requires-Dist: Click
Requires-Dist: lorem
Requires-Dist: mutagen
Requires-Dist: Pillow
Requires-Dist: qrcode
